bselib/__init__.py
bselib/analysis.py
bselib/bse.py
bselib/bulk.py
bselib/corporate.py
bselib/gainers.py
bselib/getId.py
bselib/holdings.py
bselib/index.py
bselib/kyc.py
bselib/losers.py
bselib/news.py
bselib/peers.py
bselib/quote.py
bselib/ratios.py
bselib/script.py
bselib/statements.py
bselib/stmt_analysis.py
bselib-0.0.5.dist-info/LICENSE
bselib-0.0.5.dist-info/METADATA
bselib-0.0.5.dist-info/WHEEL
bselib-0.0.5.dist-info/top_level.txt
bselib-0.0.5.dist-info/RECORD
