Metadata-Version: 2.1
Name: bselib
Version: 0.0.5
Summary: A package for stocks data listed on Bombay Stock Exchange
Home-page: https://github.com/Sachin-Kahandal/bselib
Author: Sachin Kahandal
Author-email: sachinkahandal142@gmail.com
License: MIT
Platform: UNKNOWN
Classifier: Programming Language :: Python :: 2.7
Classifier: Programming Language :: Python :: 3.5
Classifier: Programming Language :: Python :: 3.6
Classifier: Programming Language :: Python :: 3.7
Classifier: License :: OSI Approved :: MIT License
Classifier: Operating System :: OS Independent
Classifier: Intended Audience :: Developers
Classifier: Intended Audience :: Information Technology
